{
    "version": "https://jsonfeed.org/version/1",
    "title": "Iterating",
    "description": "",
    "home_page_url": "https://iterating.com",
    "feed_url": "https://iterating.com/feed.json",
    "user_comment": "",
    "author": {
        "name": "𖤂"
    },
    "items": [
        {
            "id": "https://iterating.com/we-go/",
            "url": "https://iterating.com/we-go/",
            "title": "We Go",
            "summary": "One of the best dudes I know was a Blackhawk helicopter&hellip;",
            "content_html": "<p>One of the best dudes I know was a Blackhawk helicopter pilot.</p>\n<p>By the time I knew him, he was a 1L in law school.</p>\n<p>But he and I quickly bonded over the repetitive lifting of heavy objects.</p>\n<p>And we quickly became good friends.</p>\n<p>He loved to quote a movie I'd never seen.</p>\n<p><em>Backdraft</em>.</p>\n<p>It's a movie about firefighters.</p>\n<p>Apparently, there's a part where the two main characters are fighting a fire that overtakes them.</p>\n<p>One gets into dire trouble and the other holds onto him for dear life.</p>\n<p>The one in peril tells the other to leave him, to let him go, to get out and get to safety.</p>\n<p>And the line my buddy quotes, is the other guy's response:</p>\n<blockquote>\n<p>\"If you go, we go.\"</p>\n</blockquote>\n<p>He was the ultimate got-your-back, share-a-foxhole, dude.</p>\n<p>A good man.</p>\n<p>A badmf.</p>\n<p><em>How many of those are left?</em></p>\n<p>Have the pleasure of knowing many.</p>\n<p>But like all old(ish) men, we have lost touch over the years.</p>\n<p>My fault (as most things are of this ilk).</p>\n<p>But I remember the line.</p>\n<p>If you go...</p>\n<p>🚁</p>\n<p>And so I ask, are you like that?</p>\n<p>And with who?</p>\n<p>Who's your \"If you go?\"</p>\n<p>And does anyone \"If you go\" about you?</p>",
            "author": {
                "name": "𖤂"
            },
            "tags": [
            ],
            "date_published": "2026-05-17T16:09:59-04:00",
            "date_modified": "2026-05-17T16:23:13-04:00"
        },
        {
            "id": "https://iterating.com/snooze-button/",
            "url": "https://iterating.com/snooze-button/",
            "title": "Snooze Button",
            "summary": "I'll keep this short and sweet. Because I have no idea&hellip;",
            "content_html": "<p>I'll keep this short and sweet.</p>\n<p>Because I have no idea what I'm going to say.</p>\n<p>So how are youuuuuuuu?</p>\n<p>How's life?</p>\n<p><em>Zzzzzzzzzzz</em>.</p>",
            "author": {
                "name": "𖤂"
            },
            "tags": [
            ],
            "date_published": "2026-05-16T13:29:40-04:00",
            "date_modified": "2026-05-16T13:29:40-04:00"
        },
        {
            "id": "https://iterating.com/wrong-in-all-the-right-ways/",
            "url": "https://iterating.com/wrong-in-all-the-right-ways/",
            "title": "Wrong In All The Right Ways",
            "summary": "If your operating system has been wrecked before, any new issues&hellip;",
            "content_html": "<p>If your operating system has been wrecked before, any new issues make you wonder.</p>\n<p><em>Is this related to that big one?</em></p>\n<p>Often, it is unrelated.</p>\n<p>But you look through a different filter once it happens.</p>\n<p>Everything is post-wreck view.</p>\n<p>And so it is, with many of us, with tread on our tires.</p>\n<p>Our reality.</p>\n<p>Any time something goes awry, we tend to blame the big one.</p>\n<p>It's a lens I wear now.</p>\n<p>Old folks used to say things like \"My bum knee is acting up again.\"</p>\n<p>And as a youngin, you wouldn't understand.</p>\n<p>It was almost funny.</p>\n<p>And as an old(ish) man, well my bum knee acts up.</p>\n<p>Not all the time, you see.</p>\n<p>Just when it's in a mood to act up.</p>\n<p>And that's interesting right?</p>\n<p>We are a system onto ourselves.</p>\n<p>Often cooperating, but constantly fighting.</p>\n<p>Cycling.</p>\n<p>Iterating.</p>\n<p>Good days.</p>\n<p>Bad days.</p>\n<p>Every day, a good 'un.</p>\n<p>Sometimes, you have to kill a part of you, so the rest can live.</p>\n<p>I'm talking literally and figuratively, here.</p>\n<p>As I am wont to do.</p>\n<p>I have.</p>\n<p>You have, too.</p>\n<p>Or will, if you live long enough.</p>\n<p>To everyone who's still out there kickin' after taking a lickin'.</p>\n<p>And if you find yourself wrapping your hands for yet another fight, know that I'm in your corner.</p>\n<p>Well, more likely, at home on my couch, eating delicious Korean food, watching you on the big screen.</p>\n<p>And rooting.</p>\n<p>This Coke Zero's for you.</p>\n<p>🍻</p>\n<p>There is no tomorrow.</p>\n<p>Fight for it anyway.</p>",
            "author": {
                "name": "𖤂"
            },
            "tags": [
            ],
            "date_published": "2026-05-15T14:03:01-04:00",
            "date_modified": "2026-05-15T14:10:34-04:00"
        },
        {
            "id": "https://iterating.com/put-me-in-coach/",
            "url": "https://iterating.com/put-me-in-coach/",
            "title": "Put Me In, Coach",
            "summary": "I have nothing to say today. Go get 'em, tiger. Oh,&hellip;",
            "content_html": "<p>I have nothing to say today.</p>\n<p>Go get 'em, tiger.</p>\n<p>Oh, a hat tip to the Harbaugh brothers' father:</p>\n<p><em>I want you to attack this day with an enthusiasm previously unknown to mankind!</em></p>\n<p>Have a great day.</p>\n<p>🐯</p>",
            "author": {
                "name": "𖤂"
            },
            "tags": [
            ],
            "date_published": "2026-05-14T13:58:26-04:00",
            "date_modified": "2026-05-14T13:59:50-04:00"
        },
        {
            "id": "https://iterating.com/family-jewels/",
            "url": "https://iterating.com/family-jewels/",
            "title": "Family Jewels",
            "summary": "Bas Rutten is a hero of mine. I don't have too&hellip;",
            "content_html": "<p>Bas Rutten is a hero of mine.</p>\n<p>I don't have too many of those.</p>\n<p>But Bas is one.</p>\n<p>And, he made a series of MMA videos back in the day.</p>\n<p>Even a how to protect yourself in the streets video.</p>\n<p>It's both hilarious and educational.</p>\n<p>Highly recommend.</p>\n<p>Anyways, in this particular self-defense video he goes on and on about the virtues of a kick to the groin.</p>\n<p>How simple it is.</p>\n<p>How effective.</p>\n<p>How we should use it.</p>\n<p><em>Everybody underestimates a kick to the groin.</em></p>\n<p>Meaning, all things being unequal, a kick to the nuggets tends to even things out.</p>\n<p><em>May the nads be ever in your favor.</em></p>\n<p>Now, as a old(ish) man of peace(ish), I would never tell you to kick someone in the chicken tenders, but do so if you need to.</p>\n<p>Do so if you must.</p>\n<p>And that's a good rule right?</p>\n<p>Fight honorably.</p>\n<p>Until you need to not.</p>\n<p>If you're in a struggle that seems like you winning means you get to live, remember to fight dirty from the start.</p>\n<p>What's fighting dirty?</p>\n<p>Well, basically take a look at what you cannot do in an organized, professional, fight.</p>\n<p>And do a whole lotta that.</p>\n<p>Piledriving. Eye-gouging. Headbutts. Throat. Using objects. Leverage. Back of the head.</p>\n<p>Read the list of no-no's and make 'em yes-yes's.</p>\n<p>Only in defense of course.</p>\n<p>When lives are at stake.</p>\n<p>Yours or your loved ones.</p>\n<p>And only if you are at a disadvantage.</p>\n<p>Fight fair until it's not.</p>\n<p><em>Oh, for many, it's never fair.</em></p>\n<p>🦶🍒</p>\n<p>Ring the bells.</p>",
            "author": {
                "name": "𖤂"
            },
            "tags": [
            ],
            "date_published": "2026-05-13T13:30:18-04:00",
            "date_modified": "2026-05-13T13:43:20-04:00"
        },
        {
            "id": "https://iterating.com/lost-and-found/",
            "url": "https://iterating.com/lost-and-found/",
            "title": "Lost and Found",
            "summary": "Why do they call it fall in love? Shouldn't it be&hellip;",
            "content_html": "<p>Why do they call it <em>fall</em> in love?</p>\n<p>Shouldn't it be <em>rise</em>?</p>\n<p>Rise in love?</p>\n<p>Soar in love?</p>\n<p><em>No, fall's right.</em></p>\n<p>Love is a strength and a weakness.</p>\n<p>I've said this before.</p>\n<p>And I'll say it again.</p>\n<p>Love is a strength and a weakness.</p>\n<p>It makes you stronger and weaker at the same time.</p>\n<p>When you love something or someone, you have a duality at play.</p>\n<p>An infinite helix of affection intertwined with concern.</p>\n<p>Joy and sorrow.</p>\n<p>Jubilance at birth.</p>\n<p>Mourned at death.</p>\n<p>Everything in between in between.</p>\n<p>Love is the most powerful thing in the universe.</p>\n<p>More powerful than hate.</p>\n<p>You've been powered by both.</p>\n<p>What say you?</p>\n<p>So you have a choice:</p>\n<p>To love or not to love.</p>\n<p>And for many years, I chose the latter.</p>\n<p>So I would remain strong.</p>\n<p>But that was weakness talking.</p>\n<p>Love's weakness is one I cannot put into words.</p>\n<p>It can cripple you.</p>\n<p>But the alternative is loneliness.</p>\n<p>Emptiness.</p>\n<p>Void.</p>\n<p>Sure, it can all end the same way.</p>\n<p>But better to have loved, I say.</p>\n<p>Than to never have loved at all.</p>\n<p>I'm missing something in the middle part.</p>\n<p>But you understand.</p>\n<p>May you know the love of loving someone more than yourself.</p>\n<p>May you know the love of having been loved by someone more than they love themselves.</p>\n<p>And may those loves fall in love.</p>\n<p>And may you all always believe it was better to have done so.</p>\n<p>Better to have loved...</p>",
            "author": {
                "name": "𖤂"
            },
            "tags": [
            ],
            "date_published": "2026-05-12T14:47:00-04:00",
            "date_modified": "2026-05-12T14:58:24-04:00"
        },
        {
            "id": "https://iterating.com/neath-the-sunshine/",
            "url": "https://iterating.com/neath-the-sunshine/",
            "title": "&#x27;Neath The Sunshine",
            "summary": "What do grandmasters do with their idle time? Their down time.",
            "content_html": "<p>What do grandmasters do with their idle time?</p>\n<p>Their down time.</p>\n<p>Their let their hair down time.</p>\n<p>They probably meditate a lot.</p>\n<p>Contemplate.</p>\n<p>Ever tinkering on their grandmastery.</p>\n<p>Do you remember the old show, <em>The People's.Court</em>?</p>\n<p>It was <em>Judge Judy</em> and all them before all them.</p>\n<p>Judge Wapner.</p>\n<p>Judge Wapner was an old curmudgeon.</p>\n<p>I am partial to them.</p>\n<p>I remember one episode years ago where someone was on the show and kept calling Judge Wapner, \"Your Majesty,\" instead of Your Honor.</p>\n<p>\"Yes, your majesty.\"</p>\n<p>\"No, I'm not royalty, call me your honor.\"</p>\n<p>\"I'm sorry your majesty, I mean, your honor!\"</p>\n<p>He kept doing it. Slipping up.</p>\n<p>Which infuriated Judge Wapner at first, then he just found it funny.</p>\n<p>Anger, then delight.</p>\n<p>Which is, as we all know, the sweet spot.</p>\n<p>I suppose I could find the clip online somewhere but I don't want to.</p>\n<p>Because I know I'll have remembered a detail wrong or got the whole show wrong.</p>\n<p>So I'll leave it in my brain.</p>\n<p>As a childhood memory.</p>\n<p>Hope all you mothers had a good day yesterday. </p>\n<p>And all days, while we're counting.</p>\n<p>And we're always counting.</p>\n<blockquote>\n<p>🎵 \"One for sorrow, two for joy...\" 🎵</p>\n</blockquote>\n<p> </p>",
            "author": {
                "name": "𖤂"
            },
            "tags": [
            ],
            "date_published": "2026-05-11T13:36:53-04:00",
            "date_modified": "2026-05-11T13:37:50-04:00"
        },
        {
            "id": "https://iterating.com/word-to-your-mother/",
            "url": "https://iterating.com/word-to-your-mother/",
            "title": "Word To Your Mother",
            "summary": "Happy Mother's Day. To you if you're a mother. And to&hellip;",
            "content_html": "<p>Happy Mother's Day.</p>\n<p>To you if you're a mother.</p>\n<p>And to your mother.</p>\n<p><em>Word.</em></p>\n<p>And the mothers around you.</p>\n<p>🤶</p>",
            "author": {
                "name": "𖤂"
            },
            "tags": [
            ],
            "date_published": "2026-05-10T13:06:46-04:00",
            "date_modified": "2026-05-10T13:06:46-04:00"
        },
        {
            "id": "https://iterating.com/strong-beginnings/",
            "url": "https://iterating.com/strong-beginnings/",
            "title": "Strong Beginnings",
            "summary": "Weekends is such a bad name for the best days of&hellip;",
            "content_html": "<p>Weekends is such a bad name for the best days of the week.</p>\n<p>Right?</p>\n<p>Week.</p>\n<p><em>Weak.</em></p>\n<p>Ends.</p>\n<p><em>It's all over.</em></p>\n<p>So what should we call it instead?</p>\n<p>Hmm.</p>\n<p>Oh, it could be anything.</p>\n<p><em>If only he put it somewhere kind of obvious.</em></p>\n<p>Tee hee.</p>\n<p>I amuse myself.</p>\n<p> </p>",
            "author": {
                "name": "𖤂"
            },
            "tags": [
            ],
            "date_published": "2026-05-09T12:20:12-04:00",
            "date_modified": "2026-05-09T12:20:12-04:00"
        },
        {
            "id": "https://iterating.com/a-whisper/",
            "url": "https://iterating.com/a-whisper/",
            "title": "A Whisper",
            "summary": "I remember a comedian doing stand-up. Talking about applying for jobs.",
            "content_html": "<p>I remember a comedian doing stand-up.</p>\n<p>Talking about applying for jobs.</p>\n<p>Living in a rough neighborhood.</p>\n<p>And how tough it is to find employment where he lives.</p>\n<p>Finally, he lands an interview. For a restaurant position.</p>\n<p>Sharing that he knew it was a bad idea when, in the middle of it, the interviewer looked him up and down and asked him, deadpan:</p>\n<p><em>\"Can you fight?\"</em></p>\n<p><em>Well, can you?</em></p>\n<p>I haven't thought about that bit in a long arse time.</p>\n<p>Still makes me chuckle.</p>\n<p>It just popped into my head when I sat down here.</p>\n<p>So here's another question.</p>\n<p>More germane to the world.</p>\n<p>Will you fight?</p>\n<p>And when?</p>\n<p>Are you doing it now?</p>\n<p>Will you do it when a line is crossed?</p>\n<p>And where is that line?</p>\n<p>There's nothing sadder to me than watching a bully hitting an innocent, and that innocent laughs it off or pretends nothing's happening as the bully continues to strike.</p>\n<p>Ever see that?</p>\n<p>It's a sad thing to see.</p>\n<p>99% of your anger is focused rightfully on the bully.</p>\n<p><em>You dirty...</em></p>\n<p>But there's 1%, 1% max, directed at the innocent.</p>\n<p><em>What are you doing? Have you no backbone?! C'mon! FIGHT BACK!!!</em></p>\n<p>Now, this is all theoretical, because, as you know, I am a old(ish) man of peace.</p>\n<p>Peace.</p>\n<p>Love.</p>\n<p>✌</p>\n<p>💛</p>\n<p>All that jazz.</p>\n<p>That's me.</p>\n<p><em>Yeah right.</em></p>\n<p>It is!</p>\n<p>I think.</p>\n<p>🤷‍♂️</p>\n<p>Me no know anymore.</p>\n<p>What are we talking about here?</p>\n<p>And what's it sound like?</p>",
            "author": {
                "name": "𖤂"
            },
            "tags": [
            ],
            "date_published": "2026-05-08T12:07:41-04:00",
            "date_modified": "2026-05-08T12:14:36-04:00"
        }
    ]
}
